{
	"start":	{
		"connected":	[{
				"socket":	5,
				"local_host":	"10.244.1.7",
				"local_port":	52646,
				"remote_host":	"10.244.2.3",
				"remote_port":	5201
			}],
		"version":	"iperf 3.12",
		"system_info":	"Linux iperf3-client 6.8.0-94-generic #96-Ubuntu SMP PREEMPT_DYNAMIC Fri Jan  9 20:36:55 UTC 2026 x86_64",
		"timestamp":	{
			"time":	"Sun, 29 Mar 2026 17:33:55 GMT",
			"timesecs":	1774805635
		},
		"connecting_to":	{
			"host":	"10.244.2.3",
			"port":	5201
		},
		"cookie":	"tmvhqmyld2wxmba5ianm7trtgl5uzvqckmxr",
		"tcp_mss_default":	1398,
		"target_bitrate":	0,
		"sock_bufsize":	0,
		"sndbuf_actual":	16384,
		"rcvbuf_actual":	131072,
		"test_start":	{
			"protocol":	"TCP",
			"num_streams":	1,
			"blksize":	131072,
			"omit":	0,
			"duration":	30,
			"bytes":	0,
			"blocks":	0,
			"reverse":	0,
			"tos":	0,
			"target_bitrate":	0
		}
	},
	"intervals":	[{
			"streams":	[{
					"socket":	5,
					"start":	0,
					"end":	1.000485,
					"seconds":	1.0004849433898926,
					"bytes":	1574830080,
					"bits_per_second":	12592533973.887365,
					"retransmits":	0,
					"snd_cwnd":	6386064,
					"snd_wnd":	5528192,
					"rtt":	65,
					"rttvar":	20,
					"pmtu":	1450,
					"omitted":	false,
					"sender":	true
				}],
			"sum":	{
				"start":	0,
				"end":	1.000485,
				"seconds":	1.0004849433898926,
				"bytes":	1574830080,
				"bits_per_second":	12592533973.887365,
				"retransmits":	0,
				"omitted":	false,
				"sender":	true
			}
		}, {
			"streams":	[{
					"socket":	5,
					"start":	1.000485,
					"end":	2.000548,
					"seconds":	1.0000629425048828,
					"bytes":	1727528960,
					"bits_per_second":	13819361854.74898,
					"retransmits":	0,
					"snd_cwnd":	6386064,
					"snd_wnd":	5528192,
					"rtt":	61,
					"rttvar":	19,
					"pmtu":	1450,
					"omitted":	false,
					"sender":	true
				}],
			"sum":	{
				"start":	1.000485,
				"end":	2.000548,
				"seconds":	1.0000629425048828,
				"bytes":	1727528960,
				"bits_per_second":	13819361854.74898,
				"retransmits":	0,
				"omitted":	false,
				"sender":	true
			}
		}, {
			"streams":	[{
					"socket":	5,
					"start":	2.000548,
					"end":	3.000494,
					"seconds":	0.9999459981918335,
					"bytes":	1748500480,
					"bits_per_second":	13988759258.293953,
					"retransmits":	0,
					"snd_cwnd":	6386064,
					"snd_wnd":	5528192,
					"rtt":	66,
					"rttvar":	20,
					"pmtu":	1450,
					"omitted":	false,
					"sender":	true
				}],
			"sum":	{
				"start":	2.000548,
				"end":	3.000494,
				"seconds":	0.9999459981918335,
				"bytes":	1748500480,
				"bits_per_second":	13988759258.293953,
				"retransmits":	0,
				"omitted":	false,
				"sender":	true
			}
		}, {
			"streams":	[{
					"socket":	5,
					"start":	3.000494,
					"end":	4.000574,
					"seconds":	1.0000799894332886,
					"bytes":	1743257600,
					"bits_per_second":	13944945351.724075,
					"retransmits":	0,
					"snd_cwnd":	6386064,
					"snd_wnd":	5528192,
					"rtt":	63,
					"rttvar":	23,
					"pmtu":	1450,
					"omitted":	false,
					"sender":	true
				}],
			"sum":	{
				"start":	3.000494,
				"end":	4.000574,
				"seconds":	1.0000799894332886,
				"bytes":	1743257600,
				"bits_per_second":	13944945351.724075,
				"retransmits":	0,
				"omitted":	false,
				"sender":	true
			}
		}, {
			"streams":	[{
					"socket":	5,
					"start":	4.000574,
					"end":	5.000217,
					"seconds":	0.99964302778244019,
					"bytes":	1748500480,
					"bits_per_second":	13992998951.866159,
					"retransmits":	0,
					"snd_cwnd":	6386064,
					"snd_wnd":	5528192,
					"rtt":	63,
					"rttvar":	21,
					"pmtu":	1450,
					"omitted":	false,
					"sender":	true
				}],
			"sum":	{
				"start":	4.000574,
				"end":	5.000217,
				"seconds":	0.99964302778244019,
				"bytes":	1748500480,
				"bits_per_second":	13992998951.866159,
				"retransmits":	0,
				"omitted":	false,
				"sender":	true
			}
		}, {
			"streams":	[{
					"socket":	5,
					"start":	5.000217,
					"end":	6.000216,
					"seconds":	0.99999898672103882,
					"bytes":	1697382400,
					"bits_per_second":	13579072959.388943,
					"retransmits":	0,
					"snd_cwnd":	6386064,
					"snd_wnd":	5528192,
					"rtt":	60,
					"rttvar":	22,
					"pmtu":	1450,
					"omitted":	false,
					"sender":	true
				}],
			"sum":	{
				"start":	5.000217,
				"end":	6.000216,
				"seconds":	0.99999898672103882,
				"bytes":	1697382400,
				"bits_per_second":	13579072959.388943,
				"retransmits":	0,
				"omitted":	false,
				"sender":	true
			}
		}, {
			"streams":	[{
					"socket":	5,
					"start":	6.000216,
					"end":	7.000006,
					"seconds":	0.9997900128364563,
					"bytes":	1726218240,
					"bits_per_second":	13812646398.43824,
					"retransmits":	0,
					"snd_cwnd":	6386064,
					"snd_wnd":	5528192,
					"rtt":	58,
					"rttvar":	19,
					"pmtu":	1450,
					"omitted":	false,
					"sender":	true
				}],
			"sum":	{
				"start":	6.000216,
				"end":	7.000006,
				"seconds":	0.9997900128364563,
				"bytes":	1726218240,
				"bits_per_second":	13812646398.43824,
				"retransmits":	0,
				"omitted":	false,
				"sender":	true
			}
		}, {
			"streams":	[{
					"socket":	5,
					"start":	7.000006,
					"end":	8.000582,
					"seconds":	1.0005760192871094,
					"bytes":	1652817920,
					"bits_per_second":	13214931304.690672,
					"retransmits":	0,
					"snd_cwnd":	6386064,
					"snd_wnd":	5528192,
					"rtt":	70,
					"rttvar":	24,
					"pmtu":	1450,
					"omitted":	false,
					"sender":	true
				}],
			"sum":	{
				"start":	7.000006,
				"end":	8.000582,
				"seconds":	1.0005760192871094,
				"bytes":	1652817920,
				"bits_per_second":	13214931304.690672,
				"retransmits":	0,
				"omitted":	false,
				"sender":	true
			}
		}, {
			"streams":	[{
					"socket":	5,
					"start":	8.000582,
					"end":	9.000017,
					"seconds":	0.999435007572174,
					"bytes":	1576796160,
					"bits_per_second":	12621500332.115448,
					"retransmits":	0,
					"snd_cwnd":	6386064,
					"snd_wnd":	5528192,
					"rtt":	66,
					"rttvar":	21,
					"pmtu":	1450,
					"omitted":	false,
					"sender":	true
				}],
			"sum":	{
				"start":	8.000582,
				"end":	9.000017,
				"seconds":	0.999435007572174,
				"bytes":	1576796160,
				"bits_per_second":	12621500332.115448,
				"retransmits":	0,
				"omitted":	false,
				"sender":	true
			}
		}, {
			"streams":	[{
					"socket":	5,
					"start":	9.000017,
					"end":	10.000592,
					"seconds":	1.0005749464035034,
					"bytes":	1572864000,
					"bits_per_second":	12575681657.059669,
					"retransmits":	0,
					"snd_cwnd":	6386064,
					"snd_wnd":	5528192,
					"rtt":	69,
					"rttvar":	24,
					"pmtu":	1450,
					"omitted":	false,
					"sender":	true
				}],
			"sum":	{
				"start":	9.000017,
				"end":	10.000592,
				"seconds":	1.0005749464035034,
				"bytes":	1572864000,
				"bits_per_second":	12575681657.059669,
				"retransmits":	0,
				"omitted":	false,
				"sender":	true
			}
		}, {
			"streams":	[{
					"socket":	5,
					"start":	10.000592,
					"end":	11.000772,
					"seconds":	1.0001800060272217,
					"bytes":	1608253440,
					"bits_per_second":	12863711974.31218,
					"retransmits":	0,
					"snd_cwnd":	6386064,
					"snd_wnd":	5528192,
					"rtt":	69,
					"rttvar":	23,
					"pmtu":	1450,
					"omitted":	false,
					"sender":	true
				}],
			"sum":	{
				"start":	10.000592,
				"end":	11.000772,
				"seconds":	1.0001800060272217,
				"bytes":	1608253440,
				"bits_per_second":	12863711974.31218,
				"retransmits":	0,
				"omitted":	false,
				"sender":	true
			}
		}, {
			"streams":	[{
					"socket":	5,
					"start":	11.000772,
					"end":	12.000687,
					"seconds":	0.99991500377655029,
					"bytes":	1736704000,
					"bits_per_second":	13894813006.631104,
					"retransmits":	0,
					"snd_cwnd":	6386064,
					"snd_wnd":	5528192,
					"rtt":	64,
					"rttvar":	21,
					"pmtu":	1450,
					"omitted":	false,
					"sender":	true
				}],
			"sum":	{
				"start":	11.000772,
				"end":	12.000687,
				"seconds":	0.99991500377655029,
				"bytes":	1736704000,
				"bits_per_second":	13894813006.631104,
				"retransmits":	0,
				"omitted":	false,
				"sender":	true
			}
		}, {
			"streams":	[{
					"socket":	5,
					"start":	12.000687,
					"end":	13.000249,
					"seconds":	0.99956202507019043,
					"bytes":	1762918400,
					"bits_per_second":	14109526819.018206,
					"retransmits":	0,
					"snd_cwnd":	6386064,
					"snd_wnd":	5528192,
					"rtt":	65,
					"rttvar":	22,
					"pmtu":	1450,
					"omitted":	false,
					"sender":	true
				}],
			"sum":	{
				"start":	12.000687,
				"end":	13.000249,
				"seconds":	0.99956202507019043,
				"bytes":	1762918400,
				"bits_per_second":	14109526819.018206,
				"retransmits":	0,
				"omitted":	false,
				"sender":	true
			}
		}, {
			"streams":	[{
					"socket":	5,
					"start":	13.000249,
					"end":	14.000088,
					"seconds":	0.99983900785446167,
					"bytes":	1734082560,
					"bits_per_second":	13874894228.991043,
					"retransmits":	0,
					"snd_cwnd":	6386064,
					"snd_wnd":	5528192,
					"rtt":	56,
					"rttvar":	16,
					"pmtu":	1450,
					"omitted":	false,
					"sender":	true
				}],
			"sum":	{
				"start":	13.000249,
				"end":	14.000088,
				"seconds":	0.99983900785446167,
				"bytes":	1734082560,
				"bits_per_second":	13874894228.991043,
				"retransmits":	0,
				"omitted":	false,
				"sender":	true
			}
		}, {
			"streams":	[{
					"socket":	5,
					"start":	14.000088,
					"end":	15.000654,
					"seconds":	1.0005660057067871,
					"bytes":	1732771840,
					"bits_per_second":	13854333088.408232,
					"retransmits":	0,
					"snd_cwnd":	6386064,
					"snd_wnd":	5528192,
					"rtt":	66,
					"rttvar":	20,
					"pmtu":	1450,
					"omitted":	false,
					"sender":	true
				}],
			"sum":	{
				"start":	14.000088,
				"end":	15.000654,
				"seconds":	1.0005660057067871,
				"bytes":	1732771840,
				"bits_per_second":	13854333088.408232,
				"retransmits":	0,
				"omitted":	false,
				"sender":	true
			}
		}, {
			"streams":	[{
					"socket":	5,
					"start":	15.000654,
					"end":	16.000693,
					"seconds":	1.0000389814376831,
					"bytes":	1706557440,
					"bits_per_second":	13651927348.24482,
					"retransmits":	0,
					"snd_cwnd":	6386064,
					"snd_wnd":	5528192,
					"rtt":	71,
					"rttvar":	22,
					"pmtu":	1450,
					"omitted":	false,
					"sender":	true
				}],
			"sum":	{
				"start":	15.000654,
				"end":	16.000693,
				"seconds":	1.0000389814376831,
				"bytes":	1706557440,
				"bits_per_second":	13651927348.24482,
				"retransmits":	0,
				"omitted":	false,
				"sender":	true
			}
		}, {
			"streams":	[{
					"socket":	5,
					"start":	16.000693,
					"end":	17.000126,
					"seconds":	0.99943298101425171,
					"bytes":	1770782720,
					"bits_per_second":	14174298856.56134,
					"retransmits":	0,
					"snd_cwnd":	6386064,
					"snd_wnd":	5528192,
					"rtt":	62,
					"rttvar":	20,
					"pmtu":	1450,
					"omitted":	false,
					"sender":	true
				}],
			"sum":	{
				"start":	16.000693,
				"end":	17.000126,
				"seconds":	0.99943298101425171,
				"bytes":	1770782720,
				"bits_per_second":	14174298856.56134,
				"retransmits":	0,
				"omitted":	false,
				"sender":	true
			}
		}, {
			"streams":	[{
					"socket":	5,
					"start":	17.000126,
					"end":	18.00013,
					"seconds":	1.0000040531158447,
					"bytes":	1709178880,
					"bits_per_second":	13673375620.224623,
					"retransmits":	0,
					"snd_cwnd":	6386064,
					"snd_wnd":	5528448,
					"rtt":	63,
					"rttvar":	21,
					"pmtu":	1450,
					"omitted":	false,
					"sender":	true
				}],
			"sum":	{
				"start":	17.000126,
				"end":	18.00013,
				"seconds":	1.0000040531158447,
				"bytes":	1709178880,
				"bits_per_second":	13673375620.224623,
				"retransmits":	0,
				"omitted":	false,
				"sender":	true
			}
		}, {
			"streams":	[{
					"socket":	5,
					"start":	18.00013,
					"end":	19.000611,
					"seconds":	1.0004810094833374,
					"bytes":	1720975360,
					"bits_per_second":	13761183620.176748,
					"retransmits":	0,
					"snd_cwnd":	6386064,
					"snd_wnd":	5528448,
					"rtt":	60,
					"rttvar":	17,
					"pmtu":	1450,
					"omitted":	false,
					"sender":	true
				}],
			"sum":	{
				"start":	18.00013,
				"end":	19.000611,
				"seconds":	1.0004810094833374,
				"bytes":	1720975360,
				"bits_per_second":	13761183620.176748,
				"retransmits":	0,
				"omitted":	false,
				"sender":	true
			}
		}, {
			"streams":	[{
					"socket":	5,
					"start":	19.000611,
					"end":	20.000569,
					"seconds":	0.99995797872543335,
					"bytes":	1696071680,
					"bits_per_second":	13569143632.710224,
					"retransmits":	0,
					"snd_cwnd":	6386064,
					"snd_wnd":	5528448,
					"rtt":	66,
					"rttvar":	19,
					"pmtu":	1450,
					"omitted":	false,
					"sender":	true
				}],
			"sum":	{
				"start":	19.000611,
				"end":	20.000569,
				"seconds":	0.99995797872543335,
				"bytes":	1696071680,
				"bits_per_second":	13569143632.710224,
				"retransmits":	0,
				"omitted":	false,
				"sender":	true
			}
		}, {
			"streams":	[{
					"socket":	5,
					"start":	20.000569,
					"end":	21.000481,
					"seconds":	0.99991202354431152,
					"bytes":	1559756800,
					"bits_per_second":	12479152271.586851,
					"retransmits":	0,
					"snd_cwnd":	6386064,
					"snd_wnd":	5528448,
					"rtt":	79,
					"rttvar":	19,
					"pmtu":	1450,
					"omitted":	false,
					"sender":	true
				}],
			"sum":	{
				"start":	20.000569,
				"end":	21.000481,
				"seconds":	0.99991202354431152,
				"bytes":	1559756800,
				"bits_per_second":	12479152271.586851,
				"retransmits":	0,
				"omitted":	false,
				"sender":	true
			}
		}, {
			"streams":	[{
					"socket":	5,
					"start":	21.000481,
					"end":	22.000498,
					"seconds":	1.0000170469284058,
					"bytes":	1564999680,
					"bits_per_second":	12519784016.138222,
					"retransmits":	0,
					"snd_cwnd":	6386064,
					"snd_wnd":	5528448,
					"rtt":	79,
					"rttvar":	20,
					"pmtu":	1450,
					"omitted":	false,
					"sender":	true
				}],
			"sum":	{
				"start":	21.000481,
				"end":	22.000498,
				"seconds":	1.0000170469284058,
				"bytes":	1564999680,
				"bits_per_second":	12519784016.138222,
				"retransmits":	0,
				"omitted":	false,
				"sender":	true
			}
		}, {
			"streams":	[{
					"socket":	5,
					"start":	22.000498,
					"end":	23.000613,
					"seconds":	1.0001150369644165,
					"bytes":	1588592640,
					"bits_per_second":	12707279313.161821,
					"retransmits":	0,
					"snd_cwnd":	6386064,
					"snd_wnd":	5528448,
					"rtt":	78,
					"rttvar":	14,
					"pmtu":	1450,
					"omitted":	false,
					"sender":	true
				}],
			"sum":	{
				"start":	22.000498,
				"end":	23.000613,
				"seconds":	1.0001150369644165,
				"bytes":	1588592640,
				"bits_per_second":	12707279313.161821,
				"retransmits":	0,
				"omitted":	false,
				"sender":	true
			}
		}, {
			"streams":	[{
					"socket":	5,
					"start":	23.000613,
					"end":	24.00027,
					"seconds":	0.99965697526931763,
					"bytes":	1494220800,
					"bits_per_second":	11957868244.534117,
					"retransmits":	0,
					"snd_cwnd":	6386064,
					"snd_wnd":	5528448,
					"rtt":	87,
					"rttvar":	22,
					"pmtu":	1450,
					"omitted":	false,
					"sender":	true
				}],
			"sum":	{
				"start":	23.000613,
				"end":	24.00027,
				"seconds":	0.99965697526931763,
				"bytes":	1494220800,
				"bits_per_second":	11957868244.534117,
				"retransmits":	0,
				"omitted":	false,
				"sender":	true
			}
		}, {
			"streams":	[{
					"socket":	5,
					"start":	24.00027,
					"end":	25.000659,
					"seconds":	1.0003889799118042,
					"bytes":	1585971200,
					"bits_per_second":	12682836231.481251,
					"retransmits":	0,
					"snd_cwnd":	6386064,
					"snd_wnd":	5528448,
					"rtt":	78,
					"rttvar":	18,
					"pmtu":	1450,
					"omitted":	false,
					"sender":	true
				}],
			"sum":	{
				"start":	24.00027,
				"end":	25.000659,
				"seconds":	1.0003889799118042,
				"bytes":	1585971200,
				"bits_per_second":	12682836231.481251,
				"retransmits":	0,
				"omitted":	false,
				"sender":	true
			}
		}, {
			"streams":	[{
					"socket":	5,
					"start":	25.000659,
					"end":	26.000675,
					"seconds":	1.0000159740448,
					"bytes":	1669857280,
					"bits_per_second":	13358644848.408728,
					"retransmits":	0,
					"snd_cwnd":	6386064,
					"snd_wnd":	5528448,
					"rtt":	93,
					"rttvar":	20,
					"pmtu":	1450,
					"omitted":	false,
					"sender":	true
				}],
			"sum":	{
				"start":	25.000659,
				"end":	26.000675,
				"seconds":	1.0000159740448,
				"bytes":	1669857280,
				"bits_per_second":	13358644848.408728,
				"retransmits":	0,
				"omitted":	false,
				"sender":	true
			}
		}, {
			"streams":	[{
					"socket":	5,
					"start":	26.000675,
					"end":	27.000138,
					"seconds":	0.99946302175521851,
					"bytes":	1625292800,
					"bits_per_second":	13009328126.182983,
					"retransmits":	0,
					"snd_cwnd":	6386064,
					"snd_wnd":	5528448,
					"rtt":	97,
					"rttvar":	34,
					"pmtu":	1450,
					"omitted":	false,
					"sender":	true
				}],
			"sum":	{
				"start":	26.000675,
				"end":	27.000138,
				"seconds":	0.99946302175521851,
				"bytes":	1625292800,
				"bits_per_second":	13009328126.182983,
				"retransmits":	0,
				"omitted":	false,
				"sender":	true
			}
		}, {
			"streams":	[{
					"socket":	5,
					"start":	27.000138,
					"end":	28.001041,
					"seconds":	1.0009030103683472,
					"bytes":	1697382400,
					"bits_per_second":	13566808231.501575,
					"retransmits":	0,
					"snd_cwnd":	6386064,
					"snd_wnd":	5528448,
					"rtt":	96,
					"rttvar":	32,
					"pmtu":	1450,
					"omitted":	false,
					"sender":	true
				}],
			"sum":	{
				"start":	27.000138,
				"end":	28.001041,
				"seconds":	1.0009030103683472,
				"bytes":	1697382400,
				"bits_per_second":	13566808231.501575,
				"retransmits":	0,
				"omitted":	false,
				"sender":	true
			}
		}, {
			"streams":	[{
					"socket":	5,
					"start":	28.001041,
					"end":	29.000301,
					"seconds":	0.99926000833511353,
					"bytes":	1684275200,
					"bits_per_second":	13484179780.645508,
					"retransmits":	0,
					"snd_cwnd":	6386064,
					"snd_wnd":	5528448,
					"rtt":	60,
					"rttvar":	19,
					"pmtu":	1450,
					"omitted":	false,
					"sender":	true
				}],
			"sum":	{
				"start":	28.001041,
				"end":	29.000301,
				"seconds":	0.99926000833511353,
				"bytes":	1684275200,
				"bits_per_second":	13484179780.645508,
				"retransmits":	0,
				"omitted":	false,
				"sender":	true
			}
		}, {
			"streams":	[{
					"socket":	5,
					"start":	29.000301,
					"end":	30.000284,
					"seconds":	0.999983012676239,
					"bytes":	1681653760,
					"bits_per_second":	13453458618.257254,
					"retransmits":	0,
					"snd_cwnd":	6386064,
					"snd_wnd":	5528448,
					"rtt":	66,
					"rttvar":	19,
					"pmtu":	1450,
					"omitted":	false,
					"sender":	true
				}],
			"sum":	{
				"start":	29.000301,
				"end":	30.000284,
				"seconds":	0.999983012676239,
				"bytes":	1681653760,
				"bits_per_second":	13453458618.257254,
				"retransmits":	0,
				"omitted":	false,
				"sender":	true
			}
		}],
	"end":	{
		"streams":	[{
				"sender":	{
					"socket":	5,
					"start":	0,
					"end":	30.000284,
					"seconds":	30.000284,
					"bytes":	50098995200,
					"bits_per_second":	13359605582.400486,
					"retransmits":	0,
					"max_snd_cwnd":	6386064,
					"max_snd_wnd":	5528448,
					"max_rtt":	97,
					"min_rtt":	56,
					"mean_rtt":	69,
					"sender":	true
				},
				"receiver":	{
					"socket":	5,
					"start":	0,
					"end":	30.008343,
					"seconds":	30.000284,
					"bytes":	50098995200,
					"bits_per_second":	13356017744.798506,
					"sender":	true
				}
			}],
		"sum_sent":	{
			"start":	0,
			"end":	30.000284,
			"seconds":	30.000284,
			"bytes":	50098995200,
			"bits_per_second":	13359605582.400486,
			"retransmits":	0,
			"sender":	true
		},
		"sum_received":	{
			"start":	0,
			"end":	30.008343,
			"seconds":	30.008343,
			"bytes":	50098995200,
			"bits_per_second":	13356017744.798506,
			"sender":	true
		},
		"cpu_utilization_percent":	{
			"host_total":	99.7273254531152,
			"host_user":	0.57188007636126426,
			"host_system":	99.155445376753946,
			"remote_total":	87.048401316977078,
			"remote_user":	1.9165988051553131,
			"remote_system":	85.131802511821761
		},
		"sender_tcp_congestion":	"cubic",
		"receiver_tcp_congestion":	"cubic"
	}
}
